headersUpdate/__init__.py
headersUpdate/headers_update.py
headersUpdate-0.1.2.dist-info/METADATA
headersUpdate-0.1.2.dist-info/WHEEL
headersUpdate-0.1.2.dist-info/top_level.txt
headersUpdate-0.1.2.dist-info/RECORD
