Metadata-Version: 2.1
Name: headersUpdate
Version: 0.1.2
Home-page: 
Author: Hex
Author-email: 
Classifier: Programming Language :: Python :: 3
Classifier: License :: OSI Approved :: MIT License
Classifier: Operating System :: OS Independent
Requires-Python: >=3.6
Requires-Dist: requests>=2.0.0
